LICENSE
README.md
rec-comp
rec-decomp
setup.cfg
setup.py
reccomp/VERSION.txt
reccomp/__info__.py
reccomp/__init__.py
reccomp/base.py
reccomp/compressor.py
reccomp/decompressor.py
recursive_compression.egg-info/PKG-INFO
recursive_compression.egg-info/SOURCES.txt
recursive_compression.egg-info/dependency_links.txt
recursive_compression.egg-info/requires.txt
recursive_compression.egg-info/top_level.txt