Metadata-Version: 2.1
Name: recursive-compression
Version: 3.5.1
Summary: Python tool for recursively (de)compressing nested archives using multiple algorithms (bzip2, rar, lzma, ...)
Home-page: https://github.com/dhondta/recursive-compression
Author: Alexandre D'Hondt
Author-email: alexandre.dhondt@gmail.com
License: GPLv3
Keywords: tinyscript,patool,tool,compression,decompression,steganography,bzip2,tar,rar,xz,arj,lzma,gzip,7z,zip
Platform: UNKNOWN
Classifier: Development Status :: 5 - Production/Stable
Classifier: Environment :: Console
Classifier: Intended Audience :: Developers
Classifier: Intended Audience :: Information Technology
Classifier: License :: OSI Approved :: GNU General Public License v3 (GPLv3)
Classifier: Programming Language :: Python :: 2
Classifier: Programming Language :: Python :: 2.7
Classifier: Programming Language :: Python :: 3
Classifier: Programming Language :: Python :: 3.6
Classifier: Programming Language :: Python :: 3.7
Classifier: Programming Language :: Python :: 3.8
Classifier: Programming Language :: Python :: 3.9
Classifier: Topic :: Software Development :: Libraries :: Python Modules
Classifier: Topic :: Security :: Cryptography
Requires-Python: !=3.0.*,!=3.1.*,!=3.2.*,!=3.3.*,!=3.4.*,!=3.5.*,<4,>=2.7
License-File: LICENSE
